azure/mgmt/computerecommender/__init__.py
azure/mgmt/computerecommender/_client.py
azure/mgmt/computerecommender/_configuration.py
azure/mgmt/computerecommender/_patch.py
azure/mgmt/computerecommender/_version.py
azure/mgmt/computerecommender/py.typed
azure/mgmt/computerecommender/_utils/__init__.py
azure/mgmt/computerecommender/_utils/model_base.py
azure/mgmt/computerecommender/_utils/serialization.py
azure/mgmt/computerecommender/aio/__init__.py
azure/mgmt/computerecommender/aio/_client.py
azure/mgmt/computerecommender/aio/_configuration.py
azure/mgmt/computerecommender/aio/_patch.py
azure/mgmt/computerecommender/aio/operations/__init__.py
azure/mgmt/computerecommender/aio/operations/_operations.py
azure/mgmt/computerecommender/aio/operations/_patch.py
azure/mgmt/computerecommender/models/__init__.py
azure/mgmt/computerecommender/models/_enums.py
azure/mgmt/computerecommender/models/_models.py
azure/mgmt/computerecommender/models/_patch.py
azure/mgmt/computerecommender/operations/__init__.py
azure/mgmt/computerecommender/operations/_operations.py
azure/mgmt/computerecommender/operations/_patch.py
azure_mgmt_computerecommender-1.0.0b1.dist-info/licenses/LICENSE
azure_mgmt_computerecommender-1.0.0b1.dist-info/METADATA
azure_mgmt_computerecommender-1.0.0b1.dist-info/WHEEL
azure_mgmt_computerecommender-1.0.0b1.dist-info/top_level.txt
azure_mgmt_computerecommender-1.0.0b1.dist-info/RECORD
